ignorefile/__init__.py
ignorefile-0.1.2.data/scripts/ignorefile
ignorefile-0.1.2.dist-info/LICENSE
ignorefile-0.1.2.dist-info/METADATA
ignorefile-0.1.2.dist-info/WHEEL
ignorefile-0.1.2.dist-info/top_level.txt
ignorefile-0.1.2.dist-info/RECORD
