Metadata-Version: 2.1
Name: ignorefile
Version: 0.1.2
Summary: Download .gitignore file for a language of your choice
Home-page: https://github.com/Otman404/ignorefile
Author: Otmane Boughaba
Author-email: otmaneboughaba@gmail.com
License: MIT
Keywords: gitignore github generate
Platform: UNKNOWN
Classifier: Intended Audience :: Developers
Classifier: Programming Language :: Python :: 3
Classifier: License :: OSI Approved :: MIT License
Classifier: Operating System :: OS Independent
Requires-Python: >=3
Requires-Dist: click (==7.1.2)
Requires-Dist: colorama (==0.4.4)
Requires-Dist: requests (==2.25.0)
